Digital Logic Class/Project 3/params.vh
`ifdef sim
  parameter timing = 20'd2;
  parameter divider1 = 32'd250;
  parameter divider2 = 32'd2500;
  parameter divider3 = 32'd125;
`else 
  parameter timing = 20'd100000;
  parameter divider1 = 32'd2500000;
  parameter divider2 = 32'd25000000;
  parameter divider3 = 32'd1250000;
`endif

Digital Logic Class/Project 3/addressFinder.v
module addressFinder (clk, address, rst);

  input clk;
  output reg [2:0] address;
  input rst;

  always @ (posedge clk, negedge rst) begin
    if (rst == 0) begin
      address <= 3'b000;
    end else begin
      if (address < 3'd7) begin
        address <= address + 1;
      end else begin
        address <= 3'b000;
      end
    end
  end

endmodule

Digital Logic Class/P3Final/Source/proj3Mem_bb.v
// megafunction wizard: %ROM: 1-PORT%VBB%
// GENERATION: STANDARD
// VERSION: WM1.0
// MODULE: altsyncram 

// ============================================================
// File Name: proj3Mem.v
// Megafunction Name(s):
// 			altsyncram
//
// Simulation Library Files(s):
// 			altera_mf
// ============================================================
// ************************************************************
// THIS IS A WIZARD-GENERATED FILE. DO NOT EDIT THIS FILE!
//
// 20.1.0 Build 711 06/05/2020 SJ Lite Edition
// ************************************************************

//Copyright (C) 2020  Intel Corporation. All rights reserved.
//Your use of Intel Corporation's design tools, logic functions 
//and other software and tools, and any partner logic 
//functions, and any output files from any of the foregoing 
//(including device programming or simulation files), and any 
//associated documentation or information are expressly subject 
//to the terms and conditions of the Intel Program License 
//Subscription Agreement, the Intel Quartus Prime License Agreement,
//the Intel FPGA IP License Agreement, or other applicable license
//agreement, including, without limitation, that your use is for
//the sole purpose of programming logic devices manufactured by
//Intel and sold by Intel or its authorized distributors.  Please
//refer to the applicable agreement for further details, at
//https://fpgasoftware.intel.com/eula.

module proj3Mem (
	address,
	clock,
	q);

	input	[2:0]  address;
	input	  clock;
	output	[3:0]  q;
`ifndef ALTERA_RESERVED_QIS
// synopsys translate_off
`endif
	tri1	  clock;
`ifndef ALTERA_RESERVED_QIS
// synopsys translate_on
`endif

endmodule

// ============================================================
// CNX file retrieval info
// ============================================================
// Retrieval info: PRIVATE: ADDRESSSTALL_A NUMERIC "0"
// Retrieval info: PRIVATE: AclrAddr NUMERIC "0"
// Retrieval info: PRIVATE: AclrByte NUMERIC "0"
// Retrieval info: PRIVATE: AclrOutput NUMERIC "0"
// Retrieval info: PRIVATE: BYTE_ENABLE NUMERIC "0"
// Retrieval info: PRIVATE: BYTE_SIZE NUMERIC "8"
// Retrieval info: PRIVATE: BlankMemory NUMERIC "0"
// Retrieval info: PRIVATE: CLOCK_ENABLE_INPUT_A NUMERIC "0"
// Retrieval info: PRIVATE: CLOCK_ENABLE_OUTPUT_A NUMERIC "0"
// Retrieval info: PRIVATE: Clken NUMERIC "0"
// Retrieval info: PRIVATE: IMPLEMENT_IN_LES NUMERIC "0"
// Retrieval info: PRIVATE: INIT_FILE_LAYOUT STRING "PORT_A"
// Retrieval info: PRIVATE: INIT_TO_SIM_X NUMERIC "0"
// Retrieval info: PRIVATE: INTENDED_DEVICE_FAMILY STRING "MAX 10"
// Retrieval info: PRIVATE: JTAG_ENABLED NUMERIC "0"
// Retrieval info: PRIVATE: JTAG_ID STRING "NONE"
// Retrieval info: PRIVATE: MAXIMUM_DEPTH NUMERIC "0"
// Retrieval info: PRIVATE: MIFfilename STRING "proj3Mem.mif"
// Retrieval info: PRIVATE: NUMWORDS_A NUMERIC "8"
// Retrieval info: PRIVATE: RAM_BLOCK_TYPE NUMERIC "0"
// Retrieval info: PRIVATE: RegAddr NUMERIC "1"
// Retrieval info: PRIVATE: RegOutput NUMERIC "0"
// Retrieval info: PRIVATE: SYNTH_WRAPPER_GEN_POSTFIX STRING "0"
// Retrieval info: PRIVATE: SingleClock NUMERIC "1"
// Retrieval info: PRIVATE: UseDQRAM NUMERIC "0"
// Retrieval info: PRIVATE: WidthAddr NUMERIC "3"
// Retrieval info: PRIVATE: WidthData NUMERIC "4"
// Retrieval info: PRIVATE: rden NUMERIC "0"
// Retrieval info: LIBRARY: altera_mf altera_mf.altera_mf_components.all
// Retrieval info: CONSTANT: ADDRESS_ACLR_A STRING "NONE"
// Retrieval info: CONSTANT: CLOCK_ENABLE_INPUT_A STRING "BYPASS"
// Retrieval info: CONSTANT: CLOCK_ENABLE_OUTPUT_A STRING "BYPASS"
// Retrieval info: CONSTANT: INIT_FILE STRING "proj3Mem.mif"
// Retrieval info: CONSTANT: INTENDED_DEVICE_FAMILY STRING "MAX 10"
// Retrieval info: CONSTANT: LPM_HINT STRING "ENABLE_RUNTIME_MOD=NO"
// Retrieval info: CONSTANT: LPM_TYPE STRING "altsyncram"
// Retrieval info: CONSTANT: NUMWORDS_A NUMERIC "8"
// Retrieval info: CONSTANT: OPERATION_MODE STRING "ROM"
// Retrieval info: CONSTANT: OUTDATA_ACLR_A STRING "NONE"
// Retrieval info: CONSTANT: OUTDATA_REG_A STRING "UNREGISTERED"
// Retrieval info: CONSTANT: WIDTHAD_A NUMERIC "3"
// Retrieval info: CONSTANT: WIDTH_A NUMERIC "4"
// Retrieval info: CONSTANT: WIDTH_BYTEENA_A NUMERIC "1"
// Retrieval info: USED_PORT: address 0 0 3 0 INPUT NODEFVAL "address[2..0]"
// Retrieval info: USED_PORT: clock 0 0 0 0 INPUT VCC "clock"
// Retrieval info: USED_PORT: q 0 0 4 0 OUTPUT NODEFVAL "q[3..0]"
// Retrieval info: CONNECT: @address_a 0 0 3 0 address 0 0 3 0
// Retrieval info: CONNECT: @clock0 0 0 0 0 clock 0 0 0 0
// Retrieval info: CONNECT: q 0 0 4 0 @q_a 0 0 4 0
// Retrieval info: GEN_FILE: TYPE_NORMAL proj3Mem.v TRUE
// Retrieval info: GEN_FILE: TYPE_NORMAL proj3Mem.inc FALSE
// Retrieval info: GEN_FILE: TYPE_NORMAL proj3Mem.cmp FALSE
// Retrieval info: GEN_FILE: TYPE_NORMAL proj3Mem.bsf FALSE
// Retrieval info: GEN_FILE: TYPE_NORMAL proj3Mem_inst.v FALSE
// Retrieval info: GEN_FILE: TYPE_NORMAL proj3Mem_bb.v TRUE
// Retrieval info: LIB_FILE: altera_mf

Digital Logic Class/Project 3/stateProcessor.v
module stateProcessor (state, leds, clk, rst);
  input [3:0] state;
  output reg [9:0] leds;
  input clk;
  input rst;

  reg [1:0] count;
  reg swit;

  always @ (posedge clk, negedge rst) begin
    if (rst == 0) begin
      count <= 0;
      swit <= 0;
      //leds <= 10'b0000000000;
    end else begin
      swit <= ~swit;
      if (count < 2'b10) begin
        count <= count + 1;
      end else begin
        count <= 2'b00;
      end
    end
  end

  always @ (*) begin
    if (state >= 4'b1000) begin //hazards
      if (swit) begin
        leds = 10'b1110000111;
      end else begin
        leds = 10'b0000000000;
      end
    end else if (state == 4'b0100 || state == 4'b0110) begin //brakes
      leds = 10'b1110000111;
    end else if (state == 4'b0000 || state == 4'b0010) begin //idle
      leds = 10'b0000000000;
    end else if (state[0] == 1) begin //turn signal handling
      if (state[1] == 0) begin //right turn
        case (count) 
          2'b00 : leds[2:0] = 3'b100; 
          2'b01 : leds[2:0] = 3'b010;
          2'b10 : leds[2:0] = 3'b001;
          default : leds[2:0] = 3'b111;
        endcase
        if (state[2] == 1) begin //brakes
          leds[9:3] = 7'b1110000;
        end else begin
          leds[9:3] = 7'b0000000;
        end
      end else if (state[1] == 1) begin //left turn
        case (count) 
          2'b00 : leds[9:7] = 3'b001; 
          2'b01 : leds[9:7] = 3'b010;
          2'b10 : leds[9:7] = 3'b100;
          default : leds[9:7] = 3'b111;
        endcase
        if (state[2] == 1) begin //brakes
          leds[6:0] = 7'b0000111;
        end else begin
          leds[6:0] = 7'b0000000;
        end
      end
    end else begin
      leds = 10'b1111111111;
    end
  end
endmodule

Digital Logic Class/P3Final/Source/sevenSeg.v
module sevenSeg (a, x);

input [3:0] a;
output reg [7:0] x;

always @ (*) begin
    case (a)
      4'b0000: x = 8'b1100_0000; //0
      4'b0001: x = 8'b1111_1001; //1
      4'b0010: x = 8'b1010_0100; //2
      4'b0011: x = 8'b1011_0000; //3
      4'b0100: x = 8'b1001_1001; //4
      4'b0101: x = 8'b1001_0010; //5
      4'b0110: x = 8'b1000_0010; //6
      4'b0111: x = 8'b1111_1000; //7
      4'b1000: x = 8'b1000_0000; //8
      4'b1001: x = 8'b1001_1000; //9
      4'b1010: x = 8'b1111_1111; //A
      4'b1011: x = 8'b1000_0011; //b
      4'b1100: x = 8'b1100_0110; //C
      4'b1101: x = 8'b1010_0001; //d
      4'b1110: x = 8'b1000_0110; //E
      4'b1111: x = 8'b1000_1110; //F
      default: x = 8'b1111_1111;
    endcase
end

endmodule

Digital Logic Class/P3Final/Source/stateDecider.v
module stateDecider (clk, state, swit, butt);
  input clk;
  output reg [3:0] state;
  input [2:0] swit;
  input [1:0] butt;
  always @ (posedge clk, negedge butt[0]) begin
    if (butt[0] == 0) begin
      state <= 4'b0000;
    end else begin
      if (swit[0] == 1) begin
        state <= 4'b1000;
      end else begin
        state[0] <= swit[1];
        state[1] <= butt[1];
        state[2] <= swit[2];
        state[3] <= swit[0];
      end
    end
  end
endmodule

Digital Logic Suffering/P2Final/Source/clk_divider.v
module clk_divider (clk, out, rst);
//`include "params.vh"

input clk;
input rst;
output reg out;

reg [31:0] count;
parameter divider = 0;

always @ (posedge clk, negedge rst) begin
  if (rst == 0) begin
    count <= 0;
    out <= 0;
  end else begin
    if (count != divider) begin
      count <= count + 1;
    end else begin
      count <= 0;
      out <= ~out;
    end
  end
end

endmodule

Digital Logic Class/Project 3/proj3.v
module proj3 (SW, HEX0, HEX1, HEX2, HEX3, HEX4, HEX5, KEY, LEDR, ADC_CLK_10);
  `include "params.vh"

  input [9:0] SW;//switches
  output [7:0] HEX0, HEX1, HEX2, HEX3, HEX4, HEX5; //Displays
  input [1:0] KEY; //buttons
  output [9:0] LEDR; //LEDs
  input ADC_CLK_10; //10 Mhz clock

  wire clk1; //?? Hz clk fast but slow
  wire clk2; //?? Hz clk slow
  wire clk3; //?? Hz clk its fast I guess
  clk_divider #(divider1) cd0 (.clk(ADC_CLK_10), .out(clk1), .rst(KEY[0]));
  clk_divider #(divider2) cd1 (.clk(ADC_CLK_10), .out(clk2), .rst(KEY[0]));
  clk_divider #(divider3) cd2 (.clk(ADC_CLK_10), .out(clk3), .rst(KEY[0]));

  wire [3:0] state; /*State the machine is in. 
  0000 = idle
  0001 = right turn
  0010 = idle
  0011 = left turn
  0100 = brake
  0101 = brake + right turn
  0111 = brake + left turn
  1000 and above = hazards
  7 unique states*/
  reg [3:0] stateHolder;
  assign state = stateHolder;

  wire [3:0] memState; 
  wire [2:0] memAddress;

  wire [3:0] baseState;

  stateDecider sd0 (.clk(clk1), .state(baseState), .swit(SW[2:0]), .butt(KEY[1:0]));

  sevenSeg ss0 (.a(state), .x(HEX0));

  stateProcessor sp0 (.state(state), .leds(LEDR), .clk(clk3), .rst(KEY[0]));

  proj3Mem m0 (.address(memAddress), .clock(ADC_CLK_10), .q(memState));

  addressFinder af0 (.clk(clk2), .address(memAddress), .rst(KEY[0]));

  always @ (*) begin
    if (SW[9] == 1) begin
      stateHolder = memState;
    end else begin
      stateHolder = baseState;
    end
  end

endmodule

Digital Logic Class/Project 3/proj3tb.v
`timescale 10ns/100ps
module proj3tb ();

reg clk = 0;
wire [7:0] DISP0, DISP1, DISP2, DISP3, DISP4, DISP5;
wire [9:0] LEDS;
reg [9:0] SWIT;
reg [1:0] BUTT;

proj3 B0 (.SW(SWIT), .HEX0(DISP0), .HEX1(DISP1), .HEX2(DISP2), .HEX3(DISP3), .HEX4(DISP4), .HEX5(DISP5), .KEY(BUTT), .LEDR(LEDS), .ADC_CLK_10(clk));

initial begin
  $dumpfile("proj3tb.vcd");
  $dumpvars;
  SWIT[9] = 0;
  BUTT[0] = 0;
  BUTT[1] = 1;
  #10 BUTT[0] = 1;
  #10 SWIT[2:0] = 3'b001; //hazards
  #2000 SWIT[2:0] = 3'b010; //Left Turn
  #2000 BUTT[1] = 0; //Right Turn
  #2000 SWIT[2:0] = 3'b110; //Right Turn + Brakes
  #2000 BUTT[1] = 1; //Left Turn + Brakes
  #2000 SWIT[2:0] = 3'b100; //Brakes
  #2000 SWIT[2:0] = 3'b000; //Idle
  #2000 $finish;
end


always #1 clk=~clk;

endmodule

Digital Logic Class/P3Final/Source/proj3tb.vcd
$date
	Sun Jan 17 04:28:55 2021
$end
$version
	Icarus Verilog
$end
$timescale
	100ps
$end
$scope module proj3tb $end
$var wire 8 ! DISP1 [7:0] $end
$var wire 8 " DISP2 [7:0] $end
$var wire 8 # DISP3 [7:0] $end
$var wire 8 $ DISP4 [7:0] $end
$var wire 8 % DISP5 [7:0] $end
$var wire 10 & LEDS [9:0] $end
$var wire 8 ' DISP0 [7:0] $end
$var reg 2 ( BUTT [1:0] $end
$var reg 10 ) SWIT [9:0] $end
$var reg 1 * clk $end
$scope module B0 $end
$var wire 1 * ADC_CLK_10 $end
$var wire 8 + HEX1 [7:0] $end
$var wire 8 , HEX2 [7:0] $end
$var wire 8 - HEX3 [7:0] $end
$var wire 8 . HEX4 [7:0] $end
$var wire 8 / HEX5 [7:0] $end
$var wire 2 0 KEY [1:0] $end
$var wire 10 1 SW [9:0] $end
$var wire 4 2 memState [3:0] $end
$var wire 4 3 state [3:0] $end
$var wire 3 4 memAddress [2:0] $end
$var wire 1 5 clk3 $end
$var wire 1 6 clk2 $end
$var wire 1 7 clk1 $end
$var wire 4 8 baseState [3:0] $end
$var wire 10 9 LEDR [9:0] $end
$var wire 8 : HEX0 [7:0] $end
$var reg 4 ; stateHolder [3:0] $end
$scope module af0 $end
$var wire 1 < rst $end
$var wire 1 6 clk $end
$var reg 3 = address [2:0] $end
$upscope $end
$scope module cd0 $end
$var wire 1 * clk $end
$var wire 1 > rst $end
$var reg 32 ? count [31:0] $end
$var reg 1 7 out $end
$upscope $end
$scope module cd1 $end
$var wire 1 * clk $end
$var wire 1 @ rst $end
$var reg 32 A count [31:0] $end
$var reg 1 6 out $end
$upscope $end
$scope module cd2 $end
$var wire 1 * clk $end
$var wire 1 B rst $end
$var reg 32 C count [31:0] $end
$var reg 1 5 out $end
$upscope $end
$scope module sd0 $end
$var wire 2 D butt [1:0] $end
$var wire 1 7 clk $end
$var wire 3 E swit [2:0] $end
$var reg 4 F state [3:0] $end
$upscope $end
$scope module sp0 $end
$var wire 1 5 clk $end
$var wire 1 G rst $end
$var wire 4 H state [3:0] $end
$var reg 2 I count [1:0] $end
$var reg 10 J leds [9:0] $end
$var reg 1 K swit $end
$upscope $end
$scope module ss0 $end
$var wire 4 L a [3:0] $end
$var reg 8 M x [7:0] $end
$upscope $end
$upscope $end
$upscope $end
$enddefinitions $end
#0
$dumpvars
b11000000 M
b0 L
0K
b0 J
b0 I
b0 H
0G
b0 F
bx E
b10 D
b0 C
0B
b0 A
0@
b0 ?
0>
b0 =
0<
b0 ;
b11000000 :
b0 9
b0 8
07
06
05
b0 4
b0 3
bz 2
b0xxxxxxxxx 1
b10 0
bz /
bz .
bz -
bz ,
bz +
0*
b0xxxxxxxxx )
b10 (
b11000000 '
b0 &
bz %
bz $
bz #
bz "
bz !
$end
#100
1*
#200
0*
#300
1*
#400
0*
#500
1*
#600
0*
#700
1*
#800
0*
#900
1*
#1000
1>
1@
1B
1G
1<
0*
b11 (
b11 0
b11 D
#1100
b1 ?
b1 A
b1 C
1*
#1200
0*
#1300
b10 ?
b10 A
b10 C
1*
#1400
0*
#1500
b11 ?
b11 A
b11 C
1*
#1600
0*
#1700
b100 ?
b100 A
b100 C
1*
#1800
0*
#1900
b101 ?
b101 A
b101 C
1*
#2000
b1 E
0*
b0xxxxxx001 )
b0xxxxxx001 1
#2100
b110 ?
b110 A
b110 C
1*
#2200
0*
#2300
b111 ?
b111 A
b111 C
1*
#2400
0*
#2500
b1000 ?
b1000 A
b1000 C
1*
#2600
0*
#2700
b1001 ?
b1001 A
b1001 C
1*
#2800
0*
#2900
b1010 ?
b1010 A
b1010 C
1*
#3000
0*
#3100
b1011 ?
b1011 A
b1011 C
1*
#3200
0*
#3300
b1100 ?
b1100 A
b1100 C
1*
#3400
0*
#3500
b1101 ?
b1101 A
b1101 C
1*
#3600
0*
#3700
b1110 ?
b1110 A
b1110 C
1*
#3800
0*
#3900
b1111 ?
b1111 A
b1111 C
1*
#4000
0*
#4100
b10000 ?
b10000 A
b10000 C
1*
#4200
0*
#4300
b10001 ?
b10001 A
b10001 C
1*
#4400
0*
#4500
b10010 ?
b10010 A
b10010 C
1*
#4600
0*
#4700
b10011 ?
b10011 A
b10011 C
1*
#4800
0*
#4900
b10100 ?
b10100 A
b10100 C
1*
#5000
0*
#5100
b10101 ?
b10101 A
b10101 C
1*
#5200
0*
#5300
b10110 ?
b10110 A
b10110 C
1*
#5400
0*
#5500
b10111 ?
b10111 A
b10111 C
1*
#5600
0*
#5700
b11000 ?
b11000 A
b11000 C
1*
#5800
0*
#5900
b11001 ?
b11001 A
b11001 C
1*
#6000
0*
#6100
b11010 ?
b11010 A
b11010 C
1*
#6200
0*
#6300
b11011 ?
b11011 A
b11011 C
1*
#6400
0*
#6500
b11100 ?
b11100 A
b11100 C
1*
#6600
0*
#6700
b11101 ?
b11101 A
b11101 C
1*
#6800
0*
#6900
b11110 ?
b11110 A
b11110 C
1*
#7000
0*
#7100
b11111 ?
b11111 A
b11111 C
1*
#7200
0*
#7300
b100000 ?
b100000 A
b100000 C
1*
#7400
0*
#7500
b100001 ?
b100001 A
b100001 C
1*
#7600
0*
#7700
b100010 ?
b100010 A
b100010 C
1*
#7800
0*
#7900
b100011 ?
b100011 A
b100011 C
1*
#8000
0*
#8100
b100100 ?
b100100 A
b100100 C
1*
#8200
0*
#8300
b100101 ?
b100101 A
b100101 C
1*
#8400
0*
#8500
b100110 ?
b100110 A
b100110 C
1*
#8600
0*
#8700
b100111 ?
b100111 A
b100111 C
1*
#8800
0*
#8900
b101000 ?
b101000 A
b101000 C
1*
#9000
0*
#9100
b101001 ?
b101001 A
b101001 C
1*
#9200
0*
#9300
b101010 ?
b101010 A
b101010 C
1*
#9400
0*
#9500
b101011 ?
b101011 A
b101011 C
1*
#9600
0*
#9700
b101100 ?
b101100 A
b101100 C
1*
#9800
0*
#9900
b101101 ?
b101101 A
b101101 C
1*
#10000
0*
#10100
b101110 ?
b101110 A
b101110 C
1*
#10200
0*
#10300
b101111 ?
b101111 A
b101111 C
1*
#10400
0*
#10500
b110000 ?
b110000 A
b110000 C
1*
#10600
0*
#10700
b110001 ?
b110001 A
b110001 C
1*
#10800
0*
#10900
b110010 ?
b110010 A
b110010 C
1*
#11000
0*
#11100
b110011 ?
b110011 A
b110011 C
1*
#11200
0*
#11300
b110100 ?
b110100 A
b110100 C
1*
#11400
0*
#11500
b110101 ?
b110101 A
b110101 C
1*
#11600
0*
#11700
b110110 ?
b110110 A
b110110 C
1*
#11800
0*
#11900
b110111 ?
b110111 A
b110111 C
1*
#12000
0*
#12100
b111000 ?
b111000 A
b111000 C
1*
#12200
0*
#12300
b111001 ?
b111001 A
b111001 C
1*
#12400
0*
#12500
b111010 ?
b111010 A
b111010 C
1*
#12600
0*
#12700
b111011 ?
b111011 A
b111011 C
1*
#12800
0*
#12900
b111100 ?
b111100 A
b111100 C
1*
#13000
0*
#13100
b111101 ?
b111101 A
b111101 C
1*
#13200
0*
#13300
b111110 ?
b111110 A
b111110 C
1*
#13400
0*
#13500
b111111 ?
b111111 A
b111111 C
1*
#13600
0*
#13700
b1000000 ?
b1000000 A
b1000000 C
1*
#13800
0*
#13900
b1000001 ?
b1000001 A
b1000001 C
1*
#14000
0*
#14100
b1000010 ?
b1000010 A
b1000010 C
1*
#14200
0*
#14300
b1000011 ?
b1000011 A
b1000011 C
1*
#14400
0*
#14500
b1000100 ?
b1000100 A
b1000100 C
1*
#14600
0*
#14700
b1000101 ?
b1000101 A
b1000101 C
1*
#14800
0*
#14900
b1000110 ?
b1000110 A
b1000110 C
1*
#15000
0*
#15100
b1000111 ?
b1000111 A
b1000111 C
1*
#15200
0*
#15300
b1001000 ?
b1001000 A
b1001000 C
1*
#15400
0*
#15500
b1001001 ?
b1001001 A
b1001001 C
1*
#15600
0*
#15700
b1001010 ?
b1001010 A
b1001010 C
1*
#15800
0*
#15900
b1001011 ?
b1001011 A
b1001011 C
1*
#16000
0*
#16100
b1001100 ?
b1001100 A
b1001100 C
1*
#16200
0*
#16300
b1001101 ?
b1001101 A
b1001101 C
1*
#16400
0*
#16500
b1001110 ?
b1001110 A
b1001110 C
1*
#16600
0*
#16700
b1001111 ?
b1001111 A
b1001111 C
1*
#16800
0*
#16900
b1010000 ?
b1010000 A
b1010000 C
1*
#17000
0*
#17100
b1010001 ?
b1010001 A
b1010001 C
1*
#17200
0*
#17300
b1010010 ?
b1010010 A
b1010010 C
1*
#17400
0*
#17500
b1010011 ?
b1010011 A
b1010011 C
1*
#17600
0*
#17700
b1010100 ?
b1010100 A
b1010100 C
1*
#17800
0*
#17900
b1010101 ?
b1010101 A
b1010101 C
1*
#18000
0*
#18100
b1010110 ?
b1010110 A
b1010110 C
1*
#18200
0*
#18300
b1010111 ?
b1010111 A
b1010111 C
1*
#18400
0*
#18500
b1011000 ?
b1011000 A
b1011000 C
1*
#18600
0*
#18700
b1011001 ?
b1011001 A
b1011001 C
1*
#18800
0*
#18900
b1011010 ?
b1011010 A
b1011010 C
1*
#19000
0*
#19100
b1011011 ?
b1011011 A
b1011011 C
1*
#19200
0*
#19300
b1011100 ?
b1011100 A
b1011100 C
1*
#19400
0*
#19500
b1011101 ?
b1011101 A
b1011101 C
1*
#19600
0*
#19700
b1011110 ?
b1011110 A
b1011110 C
1*
#19800
0*
#19900
b1011111 ?
b1011111 A
b1011111 C
1*
#20000
0*
#20100
b1100000 ?
b1100000 A
b1100000 C
1*
#20200
0*
#20300
b1100001 ?
b1100001 A
b1100001 C
1*
#20400
0*
#20500
b1100010 ?
b1100010 A
b1100010 C
1*
#20600
0*
#20700
b1100011 ?
b1100011 A
b1100011 C
1*
#20800
0*
#20900
b1100100 ?
b1100100 A
b1100100 C
1*
#21000
0*
#21100
b1100101 ?
b1100101 A
b1100101 C
1*
#21200
0*
#21300
b1100110 ?
b1100110 A
b1100110 C
1*
#21400
0*
#21500
b1100111 ?
b1100111 A
b1100111 C
1*
#21600
0*
#21700
b1101000 ?
b1101000 A
b1101000 C
1*
#21800
0*
#21900
b1101001 ?
b1101001 A
b1101001 C
1*
#22000
0*
#22100
b1101010 ?
b1101010 A
b1101010 C
1*
#22200
0*
#22300
b1101011 ?
b1101011 A
b1101011 C
1*
#22400
0*
#22500
b1101100 ?
b1101100 A
b1101100 C
1*
#22600
0*
#22700
b1101101 ?
b1101101 A
b1101101 C
1*
#22800
0*
#22900
b1101110 ?
b1101110 A
b1101110 C
1*
#23000
0*
#23100
b1101111 ?
b1101111 A
b1101111 C
1*
#23200
0*
#23300
b1110000 ?
b1110000 A
b1110000 C
1*
#23400
0*
#23500
b1110001 ?
b1110001 A
b1110001 C
1*
#23600
0*
#23700
b1110010 ?
b1110010 A
b1110010 C
1*
#23800
0*
#23900
b1110011 ?
b1110011 A
b1110011 C
1*
#24000
0*
#24100
b1110100 ?
b1110100 A
b1110100 C
1*
#24200
0*
#24300
b1110101 ?
b1110101 A
b1110101 C
1*
#24400
0*
#24500
b1110110 ?
b1110110 A
b1110110 C
1*
#24600
0*
#24700
b1110111 ?
b1110111 A
b1110111 C
1*
#24800
0*
#24900
b1111000 ?
b1111000 A
b1111000 C
1*
#25000
0*
#25100
b1111001 ?
b1111001 A
b1111001 C
1*
#25200
0*
#25300
b1111010 ?
b1111010 A
b1111010 C
1*
#25400
0*
#25500
b1111011 ?
b1111011 A
b1111011 C
1*
#25600
0*
#25700
b1111100 ?
b1111100 A
b1111100 C
1*
#25800
0*
#25900
b1111101 ?
b1111101 A
b1111101 C
1*
#26000
0*
#26100
b1 I
1K
b1111110 ?
b1111110 A
15
b0 C
1*
#26200
0*
#26300
b1111111 ?
b1111111 A
b1 C
1*
#26400
0*
#26500
b10000000 ?
b10000000 A
b10 C
1*
#26600
0*
#26700
b10000001 ?
b10000001 A
b11 C
1*
#26800
0*
#26900
b10000010 ?
b10000010 A
b100 C
1*
#27000
0*
#27100
b10000011 ?
b10000011 A
b101 C
1*
#27200
0*
#27300
b10000100 ?
b10000100 A
b110 C
1*
#27400
0*
#27500
b10000101 ?
b10000101 A
b111 C
1*
#27600
0*
#27700
b10000110 ?
b10000110 A
b1000 C
1*
#27800
0*
#27900
b10000111 ?
b10000111 A
b1001 C
1*
#28000
0*
#28100
b10001000 ?
b10001000 A
b1010 C
1*
#28200
0*
#28300
b10001001 ?
b10001001 A
b1011 C
1*
#28400
0*
#28500
b10001010 ?
b10001010 A
b1100 C
1*
#28600
0*
#28700
b10001011 ?
b10001011 A
b1101 C
1*
#28800
0*
#28900
b10001100 ?
b10001100 A
b1110 C
1*
#29000
0*
#29100
b10001101 ?
b10001101 A
b1111 C
1*
#29200
0*
#29300
b10001110 ?
b10001110 A
b10000 C
1*
#29400
0*
#29500
b10001111 ?
b10001111 A
b10001 C
1*
#29600
0*
#29700
b10010000 ?
b10010000 A
b10010 C
1*
#29800
0*
#29900
b10010001 ?
b10010001 A
b10011 C
1*
#30000
0*
#30100
b10010010 ?
b10010010 A
b10100 C
1*
#30200
0*
#30300
b10010011 ?
b10010011 A
b10101 C
1*
#30400
0*
#30500
b10010100 ?
b10010100 A
b10110 C
1*
#30600
0*
#30700
b10010101 ?
b10010101 A
b10111 C
1*
#30800
0*
#30900
b10010110 ?
b10010110 A
b11000 C
1*
#31000
0*
#31100
b10010111 ?
b10010111 A
b11001 C
1*
#31200
0*
#31300
b10011000 ?
b10011000 A
b11010 C
1*
#31400
0*
#31500
b10011001 ?
b10011001 A
b11011 C
1*
#31600
0*
#31700
b10011010 ?
b10011010 A
b11100 C
1*
#31800
0*
#31900
b10011011 ?
b10011011 A
b11101 C
1*
#32000
0*
#32100
b10011100 ?
b10011100 A
b11110 C
1*
#32200
0*
#32300
b10011101 ?
b10011101 A
b11111 C
1*
#32400
0*
#32500
b10011110 ?
b10011110 A
b100000 C
1*
#32600
0*
#32700
b10011111 ?
b10011111 A
b100001 C
1*
#32800
0*
#32900
b10100000 ?
b10100000 A
b100010 C
1*
#33000
0*
#33100
b10100001 ?
b10100001 A
b100011 C
1*
#33200
0*
#33300
b10100010 ?
b10100010 A
b100100 C
1*
#33400
0*
#33500
b10100011 ?
b10100011 A
b100101 C
1*
#33600
0*
#33700
b10100100 ?
b10100100 A
b100110 C
1*
#33800
0*
#33900
b10100101 ?
b10100101 A
b100111 C
1*
#34000
0*
#34100
b10100110 ?
b10100110 A
b101000 C
1*
#34200
0*
#34300
b10100111 ?
b10100111 A
b101001 C
1*
#34400
0*
#34500
b10101000 ?
b10101000 A
b101010 C
1*
#34600
0*
#34700
b10101001 ?
b10101001 A
b101011 C
1*
#34800
0*
#34900
b10101010 ?
b10101010 A
b101100 C
1*
#35000
0*
#35100
b10101011 ?
b10101011 A
b101101 C
1*
#35200
0*
#35300
b10101100 ?
b10101100 A
b101110 C
1*
#35400
0*
#35500
b10101101 ?
b10101101 A
b101111 C
1*
#35600
0*
#35700
b10101110 ?
b10101110 A
b110000 C
1*
#35800
0*
#35900
b10101111 ?
b10101111 A
b110001 C
1*
#36000
0*
#36100
b10110000 ?
b10110000 A
b110010 C
1*
#36200
0*
#36300
b10110001 ?
b10110001 A
b110011 C
1*
#36400
0*
#36500
b10110010 ?
b10110010 A
b110100 C
1*
#36600
0*
#36700
b10110011 ?
b10110011 A
b110101 C
1*
#36800
0*
#36900
b10110100 ?
b10110100 A
b110110 C
1*
#37000
0*
#37100
b10110101 ?
b10110101 A
b110111 C
1*
#37200
0*
#37300
b10110110 ?
b10110110 A
b111000 C
1*
#37400
0*
#37500
b10110111 ?
b10110111 A
b111001 C
1*
#37600
0*
#37700
b10111000 ?
b10111000 A
b111010 C
1*
#37800
0*
#37900
b10111001 ?
b10111001 A
b111011 C
1*
#38000
0*
#38100
b10111010 ?
b10111010 A
b111100 C
1*
#38200
0*
#38300
b10111011 ?
b10111011 A
b111101 C
1*
#38400
0*
#38500
b10111100 ?
b10111100 A
b111110 C
1*
#38600
0*
#38700
b10111101 ?
b10111101 A
b111111 C
1*
#38800
0*
#38900
b10111110 ?
b10111110 A
b1000000 C
1*
#39000
0*
#39100
b10111111 ?
b10111111 A
b1000001 C
1*
#39200
0*
#39300
b11000000 ?
b11000000 A
b1000010 C
1*
#39400
0*
#39500
b11000001 ?
b11000001 A
b1000011 C
1*
#39600
0*
#39700
b11000010 ?
b11000010 A
b1000100 C
1*
#39800
0*
#39900
b11000011 ?
b11000011 A
b1000101 C
1*
#40000
0*
#40100
b11000100 ?
b11000100 A
b1000110 C
1*
#40200
0*
#40300
b11000101 ?
b11000101 A
b1000111 C
1*
#40400
0*
#40500
b11000110 ?
b11000110 A
b1001000 C
1*
#40600
0*
#40700
b11000111 ?
b11000111 A
b1001001 C
1*
#40800
0*
#40900
b11001000 ?
b11001000 A
b1001010 C
1*
#41000
0*
#41100
b11001001 ?
b11001001 A
b1001011 C
1*
#41200
0*
#41300
b11001010 ?
b11001010 A
b1001100 C
1*
#41400
0*
#41500
b11001011 ?
b11001011 A
b1001101 C
1*
#41600
0*
#41700
b11001100 ?
b11001100 A
b1001110 C
1*
#41800
0*
#41900
b11001101 ?
b11001101 A
b1001111 C
1*
#42000
0*
#42100
b11001110 ?
b11001110 A
b1010000 C
1*
#42200
0*
#42300
b11001111 ?
b11001111 A
b1010001 C
1*
#42400
0*
#42500
b11010000 ?
b11010000 A
b1010010 C
1*
#42600
0*
