Digital Logic Class/Project 1/sevenSegNum.v
module sevenSegNum (a1, a2, b, x);

input [3:0] a1;
input [3:0] a2;
input b;
output reg [7:0] x;

always @ (*) begin
  if (b) begin
    case (a1)
      4'b0000: x = 8'b1100_0000; //0
      4'b0001: x = 8'b1111_1001; //1
      4'b0010: x = 8'b1010_0100; //2
      4'b0011: x = 8'b1011_0000; //3
      4'b0100: x = 8'b1001_1001; //4
      4'b0101: x = 8'b1001_0010; //5
      4'b0110: x = 8'b1000_0010; //6
      4'b0111: x = 8'b1111_1000; //7
      4'b1000: x = 8'b1000_0000; //8
      4'b1001: x = 8'b1001_1000; //9
      4'b1010: x = 8'b1111_1111; //off
      4'b1011: x = 8'b1100_0111; //L
      4'b1100: x = 8'b1100_0110; //C
      4'b1101: x = 8'b1010_0001; //d
      4'b1110: x = 8'b1000_0110; //E
      4'b1111: x = 8'b1000_1110; //F
      default: x = 8'b1111_1111;
    endcase
  end else begin
    case (a2)
      4'b0000: x = 8'b1100_0000; //0
      4'b0001: x = 8'b1111_1001; //1
      4'b0010: x = 8'b1010_0100; //2
      4'b0011: x = 8'b1011_0000; //3
      4'b0100: x = 8'b1001_1001; //4
      4'b0101: x = 8'b1001_0010; //5
      4'b0110: x = 8'b1000_0010; //6
      4'b0111: x = 8'b1111_1000; //7
      4'b1000: x = 8'b1000_0000; //8
      4'b1001: x = 8'b1001_1000; //9
      4'b1010: x = 8'b1111_1111; //off hex A
      4'b1011: x = 8'b1100_0111; //L hex B
      4'b1100: x = 8'b1100_0110; //C
      4'b1101: x = 8'b1010_0001; //d
      4'b1110: x = 8'b1000_0110; //E
      4'b1111: x = 8'b1000_1110; //F
      default: x = 8'b1111_1111;
    endcase
  end
end

endmodule

Digital Logic Class/Project 1/sevenSeg.v
module sevenSeg (a1, a2, b, x);

input [3:0] a1;
input [3:0] a2;
input b;
output reg [7:0] x;

always @ (*) begin
  if (b) begin
    case (a1)
      4'b0000: x = 8'b1100_0000; //0
      4'b0001: x = 8'b1111_1001; //1
      4'b0010: x = 8'b1010_0100; //2
      4'b0011: x = 8'b1011_0000; //3
      4'b0100: x = 8'b1001_1001; //4
      4'b0101: x = 8'b1001_0010; //5
      4'b0110: x = 8'b1000_0010; //6
      4'b0111: x = 8'b1111_1000; //7
      4'b1000: x = 8'b1000_0000; //8
      4'b1001: x = 8'b1001_1000; //9
      4'b1010: x = 8'b1000_1000; //A
      4'b1011: x = 8'b1000_0011; //b
      4'b1100: x = 8'b1100_0110; //C
      4'b1101: x = 8'b1010_0001; //d
      4'b1110: x = 8'b1000_0110; //E
      4'b1111: x = 8'b1000_1110; //F
      default: x = 8'b1111_1111;
    endcase
  end else begin
    case (a2)
      4'b0000: x = 8'b1100_0000; //0
      4'b0001: x = 8'b1111_1001; //1
      4'b0010: x = 8'b1010_0100; //2
      4'b0011: x = 8'b1011_0000; //3
      4'b0100: x = 8'b1001_1001; //4
      4'b0101: x = 8'b1001_0010; //5
      4'b0110: x = 8'b1000_0010; //6
      4'b0111: x = 8'b1111_1000; //7
      4'b1000: x = 8'b1000_0000; //8
      4'b1001: x = 8'b1001_1000; //9
      4'b1010: x = 8'b1000_1000; //A
      4'b1011: x = 8'b1000_0011; //b
      4'b1100: x = 8'b1100_0110; //C
      4'b1101: x = 8'b1010_0001; //d
      4'b1110: x = 8'b1000_0110; //E
      4'b1111: x = 8'b1000_1110; //F
      default: x = 8'b1111_1111;
    endcase
  end
end

endmodule

Digital Logic Class/Project 1/switchesHex.v
module switchesHex (a, w, x0, x1, x2, x3, x4, x5);

input [7:0] a;
output reg [9:0] w;
output [7:0] x0, x1, x2, x3, x4, x5;
reg [3:0] sym = 4'hA;

sevenSeg V5 (.a1(a[7:4]), .a2(4'hA), .b(1), .x(x5));
sevenSegNum V4 (.a1(4'hA), .a2(4'hA), .b(1), .x(x4));
sevenSegNum V3 (.a1(sym), .a2(4'hA), .b(1), .x(x3));
sevenSegNum V2 (.a1(4'hA), .a2(4'hA), .b(1), .x(x2));
sevenSeg V1 (.a1(a[3:0]), .a2(4'hA), .b(1), .x(x1));
sevenSegNum V0 (.a1(4'hA), .a2(4'hA), .b(1), .x(x0));

always @ (*) begin
  w[9:3] = 7'b000000;
  if (a[7:4] > a[3:0]) begin
    w[0] = 0;
    w[1] = 1;
    w[2] = 0;
    sym[3:0] = 4'hA;
  end else if (a[7:4] < a[3:0]) begin
    w[0] = 1;
    w[1] = 0;
    w[2] = 0;
    sym[3:0] = 4'hB;
  end else begin
    w[0] = 0;
    w[1] = 0;
    w[2] = 1;
    sym[3:0] = 4'hE;
  end

end

endmodule

Digital Logic Class/Project 1/switches.v
module switches (a, b, x);

input [7:0] a;
input b;
output reg [9:0] x;

always @ (*)
begin 
  x[8] = 0;
  x[9] = 0;
  if (b) begin 
     x[0] = a[0];
     x[1] = a[1];
     x[2] = a[2];
     x[3] = a[3];
     x[4] = a[4];
     x[5] = a[5];
     x[6] = a[6];
     x[7] = a[7];
  end else begin 
     x[0] = !a[0];
     x[1] = !a[1];
     x[2] = !a[2];
     x[3] = !a[3];
     x[4] = !a[4];
     x[5] = !a[5];
     x[6] = !a[6];
     x[7] = !a[7];
  end
end

endmodule

Digital Logic Class/Project 1/birthday.v
module birthday (a1, a2, b, x0, x1, x2, x3, x4, x5);

input [23:0] a1, a2;
input b;
output [7:0] x0, x1, x2, x3, x4, x5;

sevenSeg U0 (.a1(a1[23:20]), .a2(a2[23:20]), .b(b), .x(x5));
sevenSeg U1 (.a1(a1[19:16]), .a2(a2[19:16]), .b(b), .x(x4));
sevenSeg U2 (.a1(a1[15:12]), .a2(a2[15:12]), .b(b), .x(x3));
sevenSeg U3 (.a1(a1[11:8]), .a2(a2[11:8]), .b(b), .x(x2));
sevenSeg U4 (.a1(a1[7:4]), .a2(a2[7:4]), .b(b), .x(x1));
sevenSeg U5 (.a1(a1[3:0]), .a2(a2[3:0]), .b(b), .x(x0));

endmodule

Digital Logic Class/Project 1/proj1.v
module proj1 (SW, HEX0, HEX1, HEX2, HEX3, HEX4, HEX5, KEY, LEDR);

input [9:0] SW;//switches
output [7:0] HEX0, HEX1, HEX2, HEX3, HEX4, HEX5; //Displays
input [1:0] KEY; //buttons
output [9:0] LEDR; //LEDs
reg [7:0] DISP0, DISP1, DISP2, DISP3, DISP4, DISP5; //Intermediary Displays
reg [9:0] LITE0; //Intermediary LEDs
assign HEX0 = DISP0;
assign HEX1 = DISP1;
assign HEX2 = DISP2;
assign HEX3 = DISP3;
assign HEX4 = DISP4;
assign HEX5 = DISP5;
assign LEDR = LITE0;
reg [7:0] D00, D10, D20, D30, D40, D50; //Output holders for Part 1 displays
reg [7:0] D01, D11, D21, D31, D41, D51; //Output holders for Part 2 displays
reg [9:0] L0; //Output holder for Part 1 LEDs
reg [9:0] L1; //Output holders for part 2 LEDs
wire [7:0] WD0, WD1, WD2, WD3, WD4, WD5; //Output wires to assign to regs
wire [9:0] WL1; //Ouput wires to assign to regs

parameter bd0 = 24'h071201; //Felix's Birthday
//parameter bd0 = 24'b000001110001001000000001;
parameter bd1 = 24'h120997; //Thomas' Birthday

birthday b0 (.a1(bd0), .a2(bd1), .b(KEY[1]), .x0(D00), .x1(D10), .x2(D20), .x3(D30), .x4(D40), .x5(D50));
switches s0 (.a(SW[7:0]), .b(KEY[0]), .x(L0));

switchesHex s1 (.a(SW[7:0]), .w(WL1), .x0(WD0), .x1(WD1), .x2(WD2), .x3(WD3), .x4(WD4), .x5(WD5));

always @ (*) begin
  D01 = WD0;
  D11 = WD1;
  D21 = WD2;
  D31 = WD3;
  D41 = WD4;
  D51 = WD5;
  L1 = WL1;
  if (!SW[9]) begin
    DISP0 = D00;
    DISP1 = D10;
    DISP2 = D20;
    DISP3 = D30;
    DISP4 = D40;
    DISP5 = D50;
    LITE0 = L0;
  end else begin
    DISP0 = D01;
    DISP1 = D11;
    DISP2 = D21;
    DISP3 = D31;
    DISP4 = D41;
    DISP5 = D51;
    LITE0 = L1;
  end
end

endmodule

Digital Logic Class/Project 1/proj1tb.v
`timescale 1 ns / 100 ps

module proj1tb();

reg [9:0] swsin;
reg [1:0] b;


wire [9:0] x;
wire [7:0] y0; //Seven Segment Displays
wire [7:0] y1;
wire [7:0] y2;
wire [7:0] y3;
wire [7:0] y4;
wire [7:0] y5;

proj1 p1(.SW(swsin[9:0]), .HEX0(y0[7:0]), .HEX1(y1[7:0]), .HEX2(y2[7:0]), .HEX3(y3[7:0]), .HEX4(y4[7:0]), .HEX5(y5[7:0]), .KEY(b[1:0]), .LEDR(x[9:0]));
initial
  begin
    $dumpfile("proj1dump.vcd");
	  $dumpvars;

    //Design Unit 1
    $display ("Design Unit 1:");
    swsin = 10'b00_0000_0000;
    b[0] = 0;
    b[1] = 0;
    swsin = 10'b00_0000_0000;
    #10 b[0] = 1;
    #10 b[0] = 0;
    #10 swsin = 10'b01_1111_1111;
    #10 b[0] = 1;
    #10 b[1] = 1;

    #10$display ("Flipping Switch[9]...");
    #10 swsin = 10'b11_1111_1111;

    //Design Unit 2
    #10$display ("Design Unit 2:");
    //greater than
    #10 swsin = 10'b10_1111_0000;
    //less than
    #10 swsin = 10'b10_0000_1111;
    //equal to
    #10 swsin = 10'b10_0011_0011;

    #10 $finish;
  end


initial
  begin
    $monitor($time, "swsin = %10b, b = %2b, x = %10b, y0 = %7b, y1 = %7b, y2 = %7b, y3 = %7b, y4 = %7b, y5 = %7b",
    swsin, b, x, y0, y1, y2, y3, y4, y5);
  end

endmodule

Digital Logic Class/Project 1/proj1dump.vcd
$date
	Wed Oct 14 23:59:52 2020
$end
$version
	Icarus Verilog
$end
$timescale
	100ps
$end
$scope module proj1tb $end
$var wire 8 ! y5 [7:0] $end
$var wire 8 " y4 [7:0] $end
$var wire 8 # y3 [7:0] $end
$var wire 8 $ y2 [7:0] $end
$var wire 8 % y1 [7:0] $end
$var wire 8 & y0 [7:0] $end
$var wire 10 ' x [9:0] $end
$var reg 2 ( b [1:0] $end
$var reg 10 ) swsin [9:0] $end
$scope module p1 $end
$var wire 8 * HEX0 [7:0] $end
$var wire 8 + HEX1 [7:0] $end
$var wire 8 , HEX2 [7:0] $end
$var wire 8 - HEX3 [7:0] $end
$var wire 8 . HEX4 [7:0] $end
$var wire 8 / HEX5 [7:0] $end
$var wire 2 0 KEY [1:0] $end
$var wire 10 1 LEDR [9:0] $end
$var wire 10 2 SW [9:0] $end
$var wire 10 3 WL1 [9:0] $end
$var wire 8 4 WD5 [7:0] $end
$var wire 8 5 WD4 [7:0] $end
$var wire 8 6 WD3 [7:0] $end
$var wire 8 7 WD2 [7:0] $end
$var wire 8 8 WD1 [7:0] $end
$var wire 8 9 WD0 [7:0] $end
$var wire 10 : L0 [9:0] $end
$var wire 8 ; D50 [7:0] $end
$var wire 8 < D40 [7:0] $end
$var wire 8 = D30 [7:0] $end
$var wire 8 > D20 [7:0] $end
$var wire 8 ? D10 [7:0] $end
$var wire 8 @ D00 [7:0] $end
$var reg 8 A D01 [7:0] $end
$var reg 8 B D11 [7:0] $end
$var reg 8 C D21 [7:0] $end
$var reg 8 D D31 [7:0] $end
$var reg 8 E D41 [7:0] $end
$var reg 8 F D51 [7:0] $end
$var reg 8 G DISP0 [7:0] $end
$var reg 8 H DISP1 [7:0] $end
$var reg 8 I DISP2 [7:0] $end
$var reg 8 J DISP3 [7:0] $end
$var reg 8 K DISP4 [7:0] $end
$var reg 8 L DISP5 [7:0] $end
$var reg 10 M L1 [9:0] $end
$var reg 10 N LITE0 [9:0] $end
$scope module b0 $end
$var wire 24 O a1 [23:0] $end
$var wire 24 P a2 [23:0] $end
$var wire 1 Q b $end
$var wire 8 R x5 [7:0] $end
$var wire 8 S x4 [7:0] $end
$var wire 8 T x3 [7:0] $end
$var wire 8 U x2 [7:0] $end
$var wire 8 V x1 [7:0] $end
$var wire 8 W x0 [7:0] $end
$scope module U0 $end
$var wire 4 X a1 [3:0] $end
$var wire 4 Y a2 [3:0] $end
$var wire 1 Q b $end
$var reg 8 Z x [7:0] $end
$upscope $end
$scope module U1 $end
$var wire 4 [ a1 [3:0] $end
$var wire 4 \ a2 [3:0] $end
$var wire 1 Q b $end
$var reg 8 ] x [7:0] $end
$upscope $end
$scope module U2 $end
$var wire 4 ^ a1 [3:0] $end
$var wire 4 _ a2 [3:0] $end
$var wire 1 Q b $end
$var reg 8 ` x [7:0] $end
$upscope $end
$scope module U3 $end
$var wire 4 a a1 [3:0] $end
$var wire 4 b a2 [3:0] $end
$var wire 1 Q b $end
$var reg 8 c x [7:0] $end
$upscope $end
$scope module U4 $end
$var wire 4 d a1 [3:0] $end
$var wire 4 e a2 [3:0] $end
$var wire 1 Q b $end
$var reg 8 f x [7:0] $end
$upscope $end
$scope module U5 $end
$var wire 4 g a1 [3:0] $end
$var wire 4 h a2 [3:0] $end
$var wire 1 Q b $end
$var reg 8 i x [7:0] $end
$upscope $end
$upscope $end
$scope module s0 $end
$var wire 8 j a [7:0] $end
$var wire 1 k b $end
$var reg 10 l x [9:0] $end
$upscope $end
$scope module s1 $end
$var wire 8 m a [7:0] $end
$var wire 8 n x5 [7:0] $end
$var wire 8 o x4 [7:0] $end
$var wire 8 p x3 [7:0] $end
$var wire 8 q x2 [7:0] $end
$var wire 8 r x1 [7:0] $end
$var wire 8 s x0 [7:0] $end
$var reg 4 t sym [3:0] $end
$var reg 10 u w [9:0] $end
$scope module V0 $end
$var wire 4 v a1 [3:0] $end
$var wire 4 w a2 [3:0] $end
$var wire 1 x b $end
$var reg 8 y x [7:0] $end
$upscope $end
$scope module V1 $end
$var wire 4 z a1 [3:0] $end
$var wire 4 { a2 [3:0] $end
$var wire 1 | b $end
$var reg 8 } x [7:0] $end
$upscope $end
$scope module V2 $end
$var wire 4 ~ a1 [3:0] $end
$var wire 4 !" a2 [3:0] $end
$var wire 1 "" b $end
$var reg 8 #" x [7:0] $end
$upscope $end
$scope module V3 $end
$var wire 4 $" a1 [3:0] $end
$var wire 4 %" a2 [3:0] $end
$var wire 1 &" b $end
$var reg 8 '" x [7:0] $end
$upscope $end
$scope module V4 $end
$var wire 4 (" a1 [3:0] $end
$var wire 4 )" a2 [3:0] $end
$var wire 1 *" b $end
$var reg 8 +" x [7:0] $end
$upscope $end
$scope module V5 $end
$var wire 4 ," a1 [3:0] $end
$var wire 4 -" a2 [3:0] $end
$var wire 1 ." b $end
$var reg 8 /" x [7:0] $end
$upscope $end
$upscope $end
$upscope $end
$upscope $end
$enddefinitions $end
#0
$dumpvars
b11000000 /"
1."
b1010 -"
b0 ,"
b11111111 +"
1*"
b1010 )"
b1010 ("
b10000110 '"
1&"
b1010 %"
b1110 $"
b11111111 #"
1""
b1010 !"
b1010 ~
b11000000 }
1|
b1010 {
b0 z
b11111111 y
1x
b1010 w
b1010 v
b100 u
b1110 t
b11111111 s
b11000000 r
b11111111 q
b10000110 p
b11111111 o
b11000000 n
b0 m
b11111111 l
0k
b0 j
b11111000 i
b111 h
b1 g
b10011000 f
b1001 e
b0 d
b10011000 c
b1001 b
b10 a
b11000000 `
b0 _
b1 ^
b10100100 ]
b10 \
b111 [
b11111001 Z
b1 Y
b0 X
b11111000 W
b10011000 V
b10011000 U
b11000000 T
b10100100 S
b11111001 R
0Q
b100100000100110010111 P
b1110001001000000001 O
b11111111 N
b100 M
b11111001 L
b10100100 K
b11000000 J
b10011000 I
b10011000 H
b11111000 G
b11000000 F
b11111111 E
b10000110 D
b11111111 C
b11000000 B
b11111111 A
b11111000 @
b10011000 ?
b10011000 >
b11000000 =
b10100100 <
b11111001 ;
b11111111 :
b11111111 9
b11000000 8
b11111111 7
b10000110 6
b11111111 5
b11000000 4
b100 3
b0 2
b11111111 1
b0 0
b11111001 /
b10100100 .
b11000000 -
b10011000 ,
b10011000 +
b11111000 *
b0 )
b0 (
b11111111 '
b11111000 &
b10011000 %
b10011000 $
b11000000 #
b10100100 "
b11111001 !
$end
#100
b0 '
b0 1
b0 N
b0 :
b0 l
1k
b1 (
b1 0
#200
b11111111 '
b11111111 1
b11111111 N
b11111111 :
b11111111 l
0k
b0 (
b0 0
#300
b0 '
b0 1
b0 N
b10001110 F
b10001110 B
b10001110 4
b10001110 n
b10001110 /"
b10001110 8
b10001110 r
b10001110 }
b0 :
b0 l
b1111 ,"
b1111 z
b11111111 j
b11111111 m
b111111111 )
b111111111 2
#400
b11111111 '
b11111111 1
b11111111 N
b11111111 :
b11111111 l
1k
b1 (
b1 0
#500
b11000000 !
b11000000 /
b11000000 L
b11111000 "
b11111000 .
b11111000 K
b11111001 #
b11111001 -
b11111001 J
b10100100 $
b10100100 ,
b10100100 I
b11000000 %
b11000000 +
b11000000 H
b11111001 &
b11111001 *
b11111001 G
b11000000 ;
b11000000 R
b11000000 Z
b11111000 <
b11111000 S
b11111000 ]
b11111001 =
b11111001 T
b11111001 `
b10100100 >
b10100100 U
b10100100 c
b11000000 ?
b11000000 V
b11000000 f
b11111001 @
b11111001 W
b11111001 i
1Q
b11 (
b11 0
#700
b100 '
b100 1
b100 N
b10001110 !
b10001110 /
b10001110 L
b11111111 "
b11111111 .
b11111111 K
b10000110 #
b10000110 -
b10000110 J
b11111111 $
b11111111 ,
b11111111 I
b10001110 %
b10001110 +
b10001110 H
b11111111 &
b11111111 *
b11111111 G
b1111111111 )
b1111111111 2
#900
b11111111 #
b11111111 -
b11111111 J
b11111111 D
b11111111 6
b11111111 p
b11111111 '"
b10 '
b10 1
b10 N
b11000000 %
b11000000 +
b11000000 H
b10 M
b11000000 B
b11000000 8
b11000000 r
b11000000 }
b11110000 :
b11110000 l
b1010 t
b1010 $"
b10 3
b10 u
b0 z
b11110000 j
b11110000 m
b1011110000 )
b1011110000 2
#1000
b11000111 #
b11000111 -
b11000111 J
b11000111 D
b11000111 6
b11000111 p
b11000111 '"
b1 '
b1 1
b1 N
b11000000 !
b11000000 /
b11000000 L
b10001110 %
b10001110 +
b10001110 H
b1 M
b11000000 F
b10001110 B
b11000000 4
b11000000 n
b11000000 /"
b10001110 8
b10001110 r
b10001110 }
b1111 :
b1111 l
b1011 t
b1011 $"
b1 3
b1 u
b0 ,"
b1111 z
b1111 j
b1111 m
b1000001111 )
b1000001111 2
#1100
b10000110 #
b10000110 -
b10000110 J
b10000110 D
b10000110 6
b10000110 p
b10000110 '"
b100 '
b100 1
b100 N
b10110000 !
b10110000 /
b10110000 L
b10110000 %
b10110000 +
b10110000 H
b100 M
b10110000 F
b10110000 B
b10110000 4
b10110000 n
b10110000 /"
b10110000 8
b10110000 r
b10110000 }
b110011 :
b110011 l
b1110 t
b1110 $"
b100 3
b100 u
b11 ,"
b11 z
b110011 j
b110011 m
b1000110011 )
b1000110011 2
