Digital Logic Suffering/P2Final/Source/params.vh
`ifdef sim
  parameter timing = 20'd2;
  parameter divider1 = 32'd10;
  parameter divider2 = 32'd2;
`else 
  parameter timing = 20'd100000;
  parameter divider1 = 32'd2500000;
  parameter divider2 = 32'd1000000;
`endif

Digital Logic Suffering/P2Final/Source/monthProcessor.v
module monthProcesssor (doy, month, yearCount, domA);

input [7:0] doy;
input yearCount;
output reg [3:0] month;
output reg [7:0] domA;
reg [7:0] dom;

always @ (*) begin
  if (doy <= 8'd31) begin
    month = 4'h1;
    dom = doy;
  end else if (doy <= (8'd59 + yearCount)) begin
    month = 4'h2;
    dom = (doy - 31);
  end else if (doy <= (8'd90 + yearCount)) begin
    month = 4'h3;
    dom = (doy - (8'd59 + yearCount));
  end else begin
    month = 4'h4;
    dom = (doy - (8'd90 + yearCount));
  end
end

always @ (*) begin
  if (dom <= 8'd9) begin
    domA[7:4] = 8'hA;
    domA[3:0] = dom[3:0];
  end else if (dom <= 8'd19) begin
    domA[7:4] = 1;
    domA[3:0] = dom - 10;
  end else if (dom <= 8'd29) begin
    domA[7:4] = 2;
    domA[3:0] = dom - 20;    
  end else begin
    domA[7:4] = 3;
    domA[3:0] = dom - 30;
  end
end

endmodule

Digital Logic Class/P2Final/Source/counter.v
module counter (clk, out, rst);

input clk;
input rst;
output [7:0] out;

reg [7:0] count;

assign out = count;

always @ (posedge clk, negedge rst) begin
  if (rst == 0) begin
    count[3:0] <= 1;
  end else begin
    if (count[3:0] != 9) begin
      count[3:0] <= count[3:0] + 1;
    end else begin
      if (count[7:4] != 9) begin
        count[3:0] <= 0;
      end else begin
        count[3:0] <= 1;
      end
    end
  end
end

always @ (posedge clk, negedge rst) begin
  if (rst == 0) begin
    count[7:4] <= 0;
  end else begin
    if (count[3:0] == 9 && count[7:4] != 9) begin
      count[7:4] <= count[7:4] + 1;
    end else if (count[3:0] == 9 && count[7:4] == 9) begin
      count[7:4] <= 0;
    end
  end
end

endmodule

Digital Logic Suffering/P2Final/Source/clk_divider.v
module clk_divider (clk, out, rst);
//`include "params.vh"

input clk;
input rst;
output reg out;

reg [31:0] count;
parameter divider = 0;

always @ (posedge clk, negedge rst) begin
  if (rst == 0) begin
    count <= 0;
    out <= 0;
  end else begin
    if (count != divider) begin
      count <= count + 1;
    end else begin
      count <= 0;
      out <= ~out;
    end
  end
end

endmodule

Digital Logic Class/Project 2/sevenSeg.v
module sevenSeg (a1, a2, b, x);

input [3:0] a1;
input [3:0] a2;
input b;
output reg [7:0] x;

always @ (*) begin
  if (b) begin
    case (a1)
      4'b0000: x = 8'b1100_0000; //0
      4'b0001: x = 8'b1111_1001; //1
      4'b0010: x = 8'b1010_0100; //2
      4'b0011: x = 8'b1011_0000; //3
      4'b0100: x = 8'b1001_1001; //4
      4'b0101: x = 8'b1001_0010; //5
      4'b0110: x = 8'b1000_0010; //6
      4'b0111: x = 8'b1111_1000; //7
      4'b1000: x = 8'b1000_0000; //8
      4'b1001: x = 8'b1001_1000; //9
      4'b1010: x = 8'b1111_1111; //A
      4'b1011: x = 8'b1000_0011; //b
      4'b1100: x = 8'b1100_0110; //C
      4'b1101: x = 8'b1010_0001; //d
      4'b1110: x = 8'b1000_0110; //E
      4'b1111: x = 8'b1000_1110; //F
      default: x = 8'b1111_1111;
    endcase
  end else begin
    case (a2)
      4'b0000: x = 8'b1100_0000; //0
      4'b0001: x = 8'b1111_1001; //1
      4'b0010: x = 8'b1010_0100; //2
      4'b0011: x = 8'b1011_0000; //3
      4'b0100: x = 8'b1001_1001; //4
      4'b0101: x = 8'b1001_0010; //5
      4'b0110: x = 8'b1000_0010; //6
      4'b0111: x = 8'b1111_1000; //7
      4'b1000: x = 8'b1000_0000; //8
      4'b1001: x = 8'b1001_1000; //9
      4'b1010: x = 8'b1000_1000; //A
      4'b1011: x = 8'b1000_0011; //b
      4'b1100: x = 8'b1100_0110; //C
      4'b1101: x = 8'b1010_0001; //d
      4'b1110: x = 8'b1000_0110; //E
      4'b1111: x = 8'b1000_1110; //F
      default: x = 8'b1111_1111;
    endcase
  end
end

endmodule

Digital Logic Class/Project 2/proj2.v
module proj2 (SW, HEX0, HEX1, HEX2, HEX3, HEX4, HEX5, KEY, LEDR, ADC_CLK_10);
`include "params.vh"

input [9:0] SW;//switches
output [7:0] HEX0, HEX1, HEX2, HEX3, HEX4, HEX5; //Displays
input [1:0] KEY; //buttons
output [9:0] LEDR; //LEDs
input ADC_CLK_10; //10 Mhz clock

wire clk1; //2 Hz clk
wire clk2; //5 Hz clk
wire clk; //Clock being used
wire [7:0] doy; //Value of counter for display
wire [7:0] doyA; //Actual value of counter
wire [3:0] month; //Month display
wire [7:0] domA; //Day of month for display
wire [3:0] doyTens; //Day of the year for display in the tens place

assign LEDR[0] = clk;
assign clk = KEY[1] ? clk1 : clk2;
assign doyA = doy[7:4] * 10 + {4'b0, doy[3:0]};
assign doyTens = doy[7:4] ? doy[7:4] : 4'hA;

sevenSeg U0 (.a1(domA[3:0]), .a2(4'h0), .b(1'b1), .x(HEX0));
sevenSeg U1 (.a1(domA[7:4]), .a2(4'h0), .b(1'b1), .x(HEX1));
sevenSeg U2 (.a1(month), .a2(4'h0), .b(1'b1), .x(HEX2));
sevenSeg U3 (.a1(4'hA), .a2(4'h0), .b(1'b1), .x(HEX3));
sevenSeg U4 (.a1(doy[3:0]), .a2(4'h0), .b(1'b1), .x(HEX4));
sevenSeg U5 (.a1(doyTens), .a2(4'h0), .b(1'b1), .x(HEX5));

clk_divider #(divider1) cd0 (.clk(ADC_CLK_10), .out(clk1), .rst(KEY[0]));
clk_divider #(divider2) cd1 (.clk(ADC_CLK_10), .out(clk2), .rst(KEY[0]));

counter c0 (.clk(clk), .out(doy), .rst(KEY[0]));

monthProcesssor m0 (.doy(doyA), .month(month), .yearCount(SW[9]), .domA(domA));

// always @ (*) begin



// end

endmodule

Digital Logic Class/Project 2/tb_proj2.v
`timescale 10ns/100ps
module tb_proj2 ();

reg clk = 0;
wire [7:0] DISP0, DISP1, DISP2, DISP3, DISP4, DISP5;
wire [9:0] LEDS;
reg [9:0] SWIT;
reg [1:0] BUTT;

proj2 B0 (.SW(SWIT), .HEX0(DISP0), .HEX1(DISP1), .HEX2(DISP2), .HEX3(DISP3), .HEX4(DISP4), .HEX5(DISP5), .KEY(BUTT), .LEDR(LEDS), .ADC_CLK_10(clk));

initial begin
  $dumpfile("tb_proj2.vcd");
  $dumpvars;
  $dumplimit(1000000);
  //clk = 0;
  SWIT[9] = 0;
  BUTT[0] = 0;
  BUTT[1] = 1;
  #10 BUTT[0] = 1;
  #100 BUTT[1] = 0;
  #1000 SWIT[9] = 1;
  #500 BUTT[0] = 0;
  #510 BUTT[0] = 1;
  #10000 $finish;
end


always #1 clk=~clk;

endmodule

Digital Logic Suffering/P2Final/Source/tb_proj2.vcd
$date
	Wed Nov 11 23:15:20 2020
$end
$version
	Icarus Verilog
$end
$timescale
	100ps
$end
$scope module tb_proj2 $end
$var wire 10 ! LEDS [9:0] $end
$var wire 8 " DISP5 [7:0] $end
$var wire 8 # DISP4 [7:0] $end
$var wire 8 $ DISP3 [7:0] $end
$var wire 8 % DISP2 [7:0] $end
$var wire 8 & DISP1 [7:0] $end
$var wire 8 ' DISP0 [7:0] $end
$var reg 2 ( BUTT [1:0] $end
$var reg 10 ) SWIT [9:0] $end
$var reg 1 * clk $end
$scope module B0 $end
$var wire 1 * ADC_CLK_10 $end
$var wire 2 + KEY [1:0] $end
$var wire 10 , SW [9:0] $end
$var wire 4 - month [3:0] $end
$var wire 4 . doyTens [3:0] $end
$var wire 8 / doyA [7:0] $end
$var wire 8 0 doy [7:0] $end
$var wire 8 1 domA [7:0] $end
$var wire 1 2 clk2 $end
$var wire 1 3 clk1 $end
$var wire 1 4 clk $end
$var wire 10 5 LEDR [9:0] $end
$var wire 8 6 HEX5 [7:0] $end
$var wire 8 7 HEX4 [7:0] $end
$var wire 8 8 HEX3 [7:0] $end
$var wire 8 9 HEX2 [7:0] $end
$var wire 8 : HEX1 [7:0] $end
$var wire 8 ; HEX0 [7:0] $end
$scope module U0 $end
$var wire 4 < a1 [3:0] $end
$var wire 4 = a2 [3:0] $end
$var wire 1 > b $end
$var reg 8 ? x [7:0] $end
$upscope $end
$scope module U1 $end
$var wire 4 @ a1 [3:0] $end
$var wire 4 A a2 [3:0] $end
$var wire 1 B b $end
$var reg 8 C x [7:0] $end
$upscope $end
$scope module U2 $end
$var wire 4 D a2 [3:0] $end
$var wire 1 E b $end
$var wire 4 F a1 [3:0] $end
$var reg 8 G x [7:0] $end
$upscope $end
$scope module U3 $end
$var wire 4 H a1 [3:0] $end
$var wire 4 I a2 [3:0] $end
$var wire 1 J b $end
$var reg 8 K x [7:0] $end
$upscope $end
$scope module U4 $end
$var wire 4 L a1 [3:0] $end
$var wire 4 M a2 [3:0] $end
$var wire 1 N b $end
$var reg 8 O x [7:0] $end
$upscope $end
$scope module U5 $end
$var wire 4 P a1 [3:0] $end
$var wire 4 Q a2 [3:0] $end
$var wire 1 R b $end
$var reg 8 S x [7:0] $end
$upscope $end
$scope module c0 $end
$var wire 1 4 clk $end
$var wire 8 T out [7:0] $end
$var wire 1 U rst $end
$var reg 8 V count [7:0] $end
$upscope $end
$scope module cd0 $end
$var wire 1 * clk $end
$var wire 1 W rst $end
$var reg 32 X count [31:0] $end
$var reg 1 3 out $end
$upscope $end
$scope module cd1 $end
$var wire 1 * clk $end
$var wire 1 Y rst $end
$var reg 32 Z count [31:0] $end
$var reg 1 2 out $end
$upscope $end
$scope module m0 $end
$var wire 8 [ doy [7:0] $end
$var wire 1 \ yearCount $end
$var reg 8 ] dom [7:0] $end
$var reg 8 ^ domA [7:0] $end
$var reg 4 _ month [3:0] $end
$upscope $end
$upscope $end
$upscope $end
$enddefinitions $end
#0
$dumpvars
b1 _
b10100001 ^
b1 ]
0\
b1 [
b0 Z
0Y
b0 X
0W
b1 V
0U
b1 T
b11111111 S
1R
b0 Q
b1010 P
b11111001 O
1N
b0 M
b1 L
b11111111 K
1J
b0 I
b1010 H
b11111001 G
b1 F
1E
b0 D
b11111111 C
1B
b0 A
b1010 @
b11111001 ?
1>
b0 =
b1 <
b11111001 ;
b11111111 :
b11111001 9
b11111111 8
b11111001 7
b11111111 6
bz0 5
04
03
02
b10100001 1
b1 0
b1 /
b1010 .
b1 -
b0xxxxxxxxx ,
b10 +
0*
b0xxxxxxxxx )
b10 (
b11111001 '
b11111111 &
b11111001 %
b11111111 $
b11111001 #
b11111111 "
bz0 !
$end
#100
1*
#200
0*
#300
1*
#400
0*
#500
1*
#600
0*
#700
1*
#800
0*
#900
1*
#1000
1W
1Y
1U
0*
b11 (
b11 +
#1100
b1 X
b1 Z
1*
#1200
0*
#1300
b10 X
b10 Z
1*
#1400
0*
#1500
b11 X
12
b0 Z
1*
#1600
0*
#1700
b100 X
b1 Z
1*
#1800
0*
#1900
b101 X
b10 Z
1*
#2000
0*
#2100
b110 X
02
b0 Z
1*
#2200
0*
#2300
b111 X
b1 Z
1*
#2400
0*
#2500
b1000 X
b10 Z
1*
#2600
0*
#2700
b1001 X
12
b0 Z
1*
#2800
0*
#2900
b1010 X
b1 Z
1*
#3000
0*
#3100
b10100100 '
b10100100 ;
b10100100 ?
b10 <
b10100010 1
b10100010 ^
b10100100 #
b10100100 7
b10100100 O
b10 ]
b10 L
b10 /
b10 [
b10 0
b10 T
b10 V
bz1 !
bz1 5
14
13
b0 X
b10 Z
1*
#3200
0*
#3300
b1 X
02
b0 Z
1*
#3400
0*
#3500
b10 X
b1 Z
1*
#3600
0*
#3700
b11 X
b10 Z
1*
#3800
0*
#3900
b100 X
12
b0 Z
1*
#4000
0*
#4100
b101 X
b1 Z
1*
#4200
0*
#4300
b110 X
b10 Z
1*
#4400
0*
#4500
b111 X
02
b0 Z
1*
#4600
0*
#4700
b1000 X
b1 Z
1*
#4800
0*
#4900
b1001 X
b10 Z
1*
#5000
0*
#5100
b1010 X
12
b0 Z
1*
#5200
0*
#5300
bz0 !
bz0 5
04
03
b0 X
b1 Z
1*
#5400
0*
#5500
b1 X
b10 Z
1*
#5600
0*
#5700
b10 X
02
b0 Z
1*
#5800
0*
#5900
b11 X
b1 Z
1*
#6000
0*
#6100
b100 X
b10 Z
1*
#6200
0*
#6300
b101 X
12
b0 Z
1*
#6400
0*
#6500
b110 X
b1 Z
1*
#6600
0*
#6700
b111 X
b10 Z
1*
#6800
0*
#6900
b1000 X
02
b0 Z
1*
#7000
0*
#7100
b1001 X
b1 Z
1*
#7200
0*
#7300
b1010 X
b10 Z
1*
#7400
0*
#7500
b10110000 '
b10110000 ;
b10110000 ?
b11 <
b10100011 1
b10100011 ^
b10110000 #
b10110000 7
b10110000 O
b11 ]
b11 L
b11 /
b11 [
b11 0
b11 T
b11 V
bz1 !
bz1 5
14
13
b0 X
12
b0 Z
1*
#7600
0*
#7700
b1 X
b1 Z
1*
#7800
0*
#7900
b10 X
b10 Z
1*
#8000
0*
#8100
b11 X
02
b0 Z
1*
#8200
0*
#8300
b100 X
b1 Z
1*
#8400
0*
#8500
b101 X
b10 Z
1*
#8600
0*
#8700
b110 X
12
b0 Z
1*
#8800
0*
#8900
b111 X
b1 Z
1*
#9000
0*
#9100
b1000 X
b10 Z
1*
#9200
0*
#9300
b1001 X
02
b0 Z
1*
#9400
0*
#9500
b1010 X
b1 Z
1*
#9600
0*
#9700
bz0 !
bz0 5
04
03
b0 X
b10 Z
1*
#9800
0*
#9900
b1 X
12
b0 Z
1*
#10000
0*
#10100
b10 X
b1 Z
1*
#10200
0*
#10300
b11 X
b10 Z
1*
#10400
0*
#10500
b100 X
02
b0 Z
1*
#10600
0*
#10700
b101 X
b1 Z
1*
#10800
0*
#10900
b110 X
b10 Z
1*
#11000
0*
b1 (
b1 +
#11100
b10011001 '
b10011001 ;
b10011001 ?
b100 <
b10100100 1
b10100100 ^
b10011001 #
b10011001 7
b10011001 O
b100 ]
b100 L
b100 /
b100 [
b100 0
b100 T
b100 V
bz1 !
bz1 5
14
b111 X
12
b0 Z
1*
#11200
0*
#11300
b1000 X
b1 Z
1*
#11400
0*
#11500
b1001 X
b10 Z
1*
#11600
0*
#11700
bz0 !
bz0 5
04
b1010 X
02
b0 Z
1*
#11800
0*
#11900
13
b0 X
b1 Z
1*
#12000
0*
#12100
b1 X
b10 Z
1*
#12200
0*
#12300
b10010010 '
b10010010 ;
b10010010 ?
b101 <
b10100101 1
b10100101 ^
b10010010 #
b10010010 7
b10010010 O
b101 ]
b101 L
b101 /
b101 [
b101 0
b101 T
b101 V
bz1 !
bz1 5
14
b10 X
12
b0 Z
1*
#12400
0*
#12500
b11 X
b1 Z
1*
#12600
0*
#12700
b100 X
b10 Z
1*
#12800
0*
#12900
bz0 !
bz0 5
04
b101 X
02
b0 Z
1*
#13000
0*
#13100
b110 X
b1 Z
1*
#13200
0*
#13300
b111 X
b10 Z
1*
#13400
0*
#13500
b10000010 '
b10000010 ;
b10000010 ?
b110 <
b10100110 1
b10100110 ^
b10000010 #
b10000010 7
b10000010 O
b110 ]
b110 L
b110 /
b110 [
b110 0
b110 T
b110 V
bz1 !
bz1 5
14
b1000 X
12
b0 Z
1*
#13600
0*
#13700
b1001 X
b1 Z
1*
#13800
0*
#13900
b1010 X
b10 Z
1*
#14000
0*
#14100
bz0 !
bz0 5
04
03
b0 X
02
b0 Z
1*
#14200
0*
#14300
b1 X
b1 Z
1*
#14400
0*
#14500
b10 X
b10 Z
1*
#14600
0*
#14700
b11111000 '
b11111000 ;
b11111000 ?
b111 <
b10100111 1
b10100111 ^
b11111000 #
b11111000 7
b11111000 O
b111 ]
b111 L
b111 /
b111 [
b111 0
b111 T
b111 V
bz1 !
bz1 5
14
b11 X
12
b0 Z
1*
#14800
0*
#14900
b100 X
b1 Z
1*
#15000
0*
#15100
b101 X
b10 Z
1*
#15200
0*
#15300
bz0 !
bz0 5
04
b110 X
02
b0 Z
1*
#15400
0*
#15500
b111 X
b1 Z
1*
#15600
0*
#15700
b1000 X
b10 Z
1*
#15800
0*
#15900
b10000000 '
b10000000 ;
b10000000 ?
b1000 <
b10101000 1
b10101000 ^
b10000000 #
b10000000 7
b10000000 O
b1000 ]
b1000 L
b1000 /
b1000 [
b1000 0
b1000 T
b1000 V
bz1 !
bz1 5
14
b1001 X
12
b0 Z
1*
#16000
0*
#16100
b1010 X
b1 Z
1*
#16200
0*
#16300
13
b0 X
b10 Z
1*
#16400
0*
#16500
bz0 !
bz0 5
04
b1 X
02
b0 Z
1*
#16600
0*
#16700
b10 X
b1 Z
1*
#16800
0*
#16900
b11 X
b10 Z
1*
#17000
0*
#17100
b10011000 '
b10011000 ;
b10011000 ?
b1001 <
b10101001 1
b10101001 ^
b10011000 #
b10011000 7
b10011000 O
b1001 ]
b1001 L
b1001 /
b1001 [
b1001 0
b1001 T
b1001 V
bz1 !
bz1 5
14
b100 X
12
b0 Z
1*
#17200
0*
#17300
b101 X
b1 Z
1*
#17400
0*
#17500
b110 X
b10 Z
1*
#17600
0*
#17700
bz0 !
bz0 5
04
b111 X
02
b0 Z
1*
#17800
0*
#17900
b1000 X
b1 Z
1*
#18000
0*
#18100
b1001 X
b10 Z
1*
#18200
0*
#18300
b11000000 '
b11000000 ;
b11000000 ?
b11111001 &
b11111001 :
b11111001 C
b0 <
b1 @
b11111001 "
b11111001 6
b11111001 S
b10000 1
b10000 ^
b1 .
b1 P
b11000000 #
b11000000 7
b11000000 O
b1010 ]
b0 L
b1010 /
b1010 [
b10000 0
b10000 T
b10000 V
bz1 !
bz1 5
14
b1010 X
12
b0 Z
1*
#18400
0*
#18500
03
b0 X
b1 Z
1*
#18600
0*
#18700
b1 X
b10 Z
1*
#18800
0*
#18900
bz0 !
bz0 5
04
b10 X
02
b0 Z
1*
#19000
0*
#19100
b11 X
b1 Z
1*
#19200
0*
#19300
b100 X
b10 Z
1*
#19400
0*
#19500
b11111001 '
b11111001 ;
b11111001 ?
b1 <
b10001 1
b10001 ^
b11111001 #
b11111001 7
b11111001 O
b1011 ]
b1 L
b1011 /
b1011 [
b10001 0
b10001 T
b10001 V
bz1 !
bz1 5
14
b101 X
12
b0 Z
1*
#19600
0*
#19700
b110 X
b1 Z
1*
#19800
0*
#19900
b111 X
b10 Z
1*
#20000
0*
#20100
bz0 !
bz0 5
04
b1000 X
02
b0 Z
1*
#20200
0*
#20300
b1001 X
b1 Z
1*
#20400
0*
#20500
b1010 X
b10 Z
1*
#20600
0*
#20700
b10100100 '
b10100100 ;
b10100100 ?
b10 <
b10010 1
b10010 ^
b10100100 #
b10100100 7
b10100100 O
b1100 ]
b10 L
b1100 /
b1100 [
b10010 0
b10010 T
b10010 V
bz1 !
bz1 5
14
13
b0 X
12
b0 Z
1*
#20800
0*
#20900
b1 X
b1 Z
1*
#21000
0*
#21100
b10 X
b10 Z
1*
#21200
0*
#21300
bz0 !
bz0 5
04
b11 X
02
b0 Z
1*
#21400
0*
#21500
b100 X
b1 Z
1*
#21600
0*
#21700
b101 X
b10 Z
1*
#21800
0*
#21900
b10110000 '
b10110000 ;
b10110000 ?
b11 <
b10011 1
b10011 ^
b10110000 #
b10110000 7
b10110000 O
b1101 ]
b11 L
b1101 /
b1101 [
b10011 0
b10011 T
b10011 V
bz1 !
bz1 5
14
b110 X
12
b0 Z
1*
#22000
0*
#22100
b111 X
b1 Z
1*
#22200
0*
#22300
b1000 X
b10 Z
1*
#22400
0*
#22500
bz0 !
bz0 5
04
b1001 X
02
b0 Z
1*
#22600
0*
#22700
b1010 X
b1 Z
1*
#22800
0*
#22900
03
b0 X
b10 Z
1*
#23000
0*
#23100
b10011001 '
b10011001 ;
b10011001 ?
b100 <
b10100 1
b10100 ^
b10011001 #
b10011001 7
b10011001 O
b1110 ]
b100 L
b1110 /
b1110 [
b10100 0
b10100 T
b10100 V
bz1 !
bz1 5
14
b1 X
12
b0 Z
1*
#23200
0*
#23300
b10 X
b1 Z
1*
#23400
0*
#23500
b11 X
b10 Z
1*
#23600
0*
#23700
bz0 !
bz0 5
04
b100 X
02
b0 Z
1*
#23800
0*
#23900
b101 X
b1 Z
1*
#24000
0*
#24100
b110 X
b10 Z
1*
#24200
0*
#24300
b10010010 '
b10010010 ;
b10010010 ?
b101 <
b10101 1
b10101 ^
b10010010 #
b10010010 7
b10010010 O
b1111 ]
b101 L
b1111 /
b1111 [
b10101 0
b10101 T
b10101 V
bz1 !
bz1 5
14
b111 X
12
b0 Z
1*
#24400
0*
#24500
b1000 X
b1 Z
1*
#24600
0*
#24700
b1001 X
b10 Z
1*
#24800
0*
#24900
bz0 !
bz0 5
04
b1010 X
02
b0 Z
1*
#25000
0*
#25100
13
b0 X
b1 Z
1*
#25200
0*
#25300
b1 X
b10 Z
1*
#25400
0*
#25500
b10000010 '
b10000010 ;
b10000010 ?
b110 <
b10110 1
b10110 ^
b10000010 #
b10000010 7
b10000010 O
b10000 ]
b110 L
b10000 /
b10000 [
b10110 0
b10110 T
b10110 V
bz1 !
bz1 5
14
b10 X
12
b0 Z
1*
#25600
0*
#25700
b11 X
b1 Z
1*
#25800
0*
#25900
b100 X
b10 Z
1*
#26000
0*
#26100
bz0 !
bz0 5
04
b101 X
02
b0 Z
1*
#26200
0*
#26300
b110 X
b1 Z
1*
#26400
0*
#26500
b111 X
b10 Z
1*
#26600
0*
#26700
b11111000 '
b11111000 ;
b11111000 ?
b111 <
b10111 1
b10111 ^
b11111000 #
b11111000 7
b11111000 O
b10001 ]
b111 L
b10001 /
b10001 [
b10111 0
b10111 T
b10111 V
bz1 !
bz1 5
14
b1000 X
12
b0 Z
1*
#26800
0*
#26900
b1001 X
b1 Z
1*
#27000
0*
#27100
b1010 X
b10 Z
1*
#27200
0*
#27300
bz0 !
bz0 5
04
03
b0 X
02
b0 Z
1*
#27400
0*
#27500
b1 X
b1 Z
1*
#27600
0*
#27700
b10 X
b10 Z
1*
#27800
0*
#27900
b10000000 '
b10000000 ;
b10000000 ?
b1000 <
b11000 1
b11000 ^
b10000000 #
b10000000 7
b10000000 O
b10010 ]
b1000 L
b10010 /
b10010 [
b11000 0
b11000 T
b11000 V
bz1 !
bz1 5
14
b11 X
12
b0 Z
1*
#28000
0*
#28100
b100 X
b1 Z
1*
#28200
0*
#28300
b101 X
b10 Z
1*
#28400
0*
#28500
bz0 !
bz0 5
04
b110 X
02
b0 Z
1*
#28600
0*
#28700
b111 X
b1 Z
1*
#28800
0*
#28900
b1000 X
b10 Z
1*
#29000
0*
#29100
b10011000 '
b10011000 ;
b10011000 ?
b1001 <
b11001 1
b11001 ^
b10011000 #
b10011000 7
b10011000 O
b10011 ]
b1001 L
b10011 /
b10011 [
b11001 0
b11001 T
b11001 V
bz1 !
bz1 5
14
b1001 X
12
b0 Z
1*
#29200
0*
#29300
b1010 X
b1 Z
1*
#29400
0*
#29500
13
b0 X
b10 Z
1*
#29600
0*
#29700
bz0 !
bz0 5
04
b1 X
02
b0 Z
1*
#29800
0*
#29900
b10 X
b1 Z
1*
#30000
0*
#30100
b11 X
b10 Z
1*
#30200
0*
#30300
b11000000 '
b11000000 ;
b11000000 ?
b10100100 &
b10100100 :
b10100100 C
b0 <
b10 @
b10100100 "
b10100100 6
b10100100 S
b100000 1
b100000 ^
b10 .
b10 P
b11000000 #
b11000000 7
b11000000 O
b10100 ]
b0 L
b10100 /
b10100 [
b100000 0
b100000 T
b100000 V
bz1 !
bz1 5
14
b100 X
12
b0 Z
1*
#30400
0*
#30500
b101 X
b1 Z
1*
#30600
0*
#30700
b110 X
b10 Z
1*
#30800
0*
#30900
bz0 !
bz0 5
04
b111 X
02
b0 Z
1*
#31000
0*
#31100
b1000 X
b1 Z
1*
#31200
0*
#31300
b1001 X
b10 Z
1*
#31400
0*
#31500
b11111001 '
b11111001 ;
b11111001 ?
b1 <
b100001 1
b100001 ^
b11111001 #
b11111001 7
b11111001 O
b10101 ]
b1 L
b10101 /
b10101 [
b100001 0
b100001 T
b100001 V
bz1 !
bz1 5
14
b1010 X
12
b0 Z
1*
#31600
0*
#31700
03
b0 X
b1 Z
1*
#31800
0*
#31900
b1 X
b10 Z
1*
#32000
0*
#32100
bz0 !
bz0 5
04
b10 X
02
b0 Z
1*
#32200
0*
#32300
b11 X
b1 Z
1*
#32400
0*
#32500
b100 X
b10 Z
1*
#32600
0*
#32700
b10100100 '
b10100100 ;
b10100100 ?
b10 <
b100010 1
b100010 ^
b10100100 #
b10100100 7
b10100100 O
b10110 ]
b10 L
b10110 /
b10110 [
b100010 0
b100010 T
b100010 V
bz1 !
bz1 5
14
b101 X
12
b0 Z
1*
#32800
0*
#32900
b110 X
b1 Z
1*
#33000
0*
#33100
b111 X
b10 Z
1*
#33200
0*
#33300
bz0 !
bz0 5
04
b1000 X
02
b0 Z
1*
#33400
0*
#33500
b1001 X
b1 Z
1*
#33600
0*
#33700
b1010 X
b10 Z
1*
#33800
0*
#33900
b10110000 '
b10110000 ;
b10110000 ?
b11 <
b100011 1
b100011 ^
b10110000 #
b10110000 7
b10110000 O
b10111 ]
b11 L
b10111 /
b10111 [
b100011 0
b100011 T
b100011 V
bz1 !
bz1 5
14
13
b0 X
12
b0 Z
1*
#34000
0*
#34100
b1 X
b1 Z
1*
#34200
0*
#34300
b10 X
b10 Z
1*
#34400
0*
#34500
bz0 !
bz0 5
04
b11 X
02
b0 Z
1*
#34600
0*
#34700
b100 X
b1 Z
1*
#34800
0*
#34900
b101 X
b10 Z
1*
#35000
0*
#35100
b10011001 '
b10011001 ;
b10011001 ?
b100 <
b100100 1
b100100 ^
b10011001 #
b10011001 7
b10011001 O
b11000 ]
b100 L
b11000 /
b11000 [
b100100 0
b100100 T
b100100 V
bz1 !
bz1 5
14
b110 X
12
b0 Z
1*
#35200
0*
#35300
b111 X
b1 Z
1*
#35400
0*
#35500
b1000 X
b10 Z
1*
#35600
0*
#35700
bz0 !
bz0 5
04
b1001 X
02
b0 Z
1*
#35800
0*
#35900
b1010 X
b1 Z
1*
#36000
0*
#36100
03
b0 X
b10 Z
1*
#36200
0*
#36300
b10010010 '
b10010010 ;
b10010010 ?
b101 <
b100101 1
b100101 ^
b10010010 #
b10010010 7
b10010010 O
b11001 ]
b101 L
b11001 /
b11001 [
b100101 0
b100101 T
b100101 V
bz1 !
bz1 5
14
b1 X
12
b0 Z
1*
#36400
0*
#36500
b10 X
b1 Z
1*
#36600
0*
#36700
b11 X
b10 Z
1*
#36800
0*
#36900
bz0 !
bz0 5
04
b100 X
02
b0 Z
1*
#37000
0*
#37100
b101 X
b1 Z
1*
#37200
0*
#37300
b110 X
b10 Z
1*
#37400
0*
#37500
b10000010 '
b10000010 ;
b10000010 ?
b110 <
b100110 1
b100110 ^
b10000010 #
b10000010 7
b10000010 O
b11010 ]
b110 L
b11010 /
b11010 [
b100110 0
b100110 T
b100110 V
bz1 !
bz1 5
14
b111 X
12
b0 Z
1*
#37600
0*
#37700
b1000 X
b1 Z
1*
#37800
0*
#37900
b1001 X
b10 Z
1*
#38000
0*
#38100
bz0 !
bz0 5
04
b1010 X
02
b0 Z
1*
#38200
0*
#38300
13
b0 X
b1 Z
1*
#38400
0*
#38500
b1 X
b10 Z
1*
#38600
0*
#38700
b11111000 '
b11111000 ;
b11111000 ?
b111 <
b100111 1
b100111 ^
b11111000 #
b11111000 7
b11111000 O
b11011 ]
b111 L
b11011 /
b11011 [
b100111 0
b100111 T
b100111 V
bz1 !
bz1 5
14
b10 X
12
b0 Z
1*
#38800
0*
#38900
b11 X
b1 Z
1*
#39000
0*
#39100
b100 X
b10 Z
1*
#39200
0*
#39300
bz0 !
bz0 5
04
b101 X
02
b0 Z
1*
#39400
0*
#39500
b110 X
b1 Z
1*
#39600
0*
#39700
b111 X
b10 Z
1*
#39800
0*
#39900
b10000000 '
b10000000 ;
b10000000 ?
b1000 <
b101000 1
b101000 ^
b10000000 #
b10000000 7
b10000000 O
b11100 ]
b1000 L
b11100 /
b11100 [
b101000 0
b101000 T
b101000 V
bz1 !
bz1 5
14
b1000 X
12
b0 Z
1*
#40000
0*
#40100
b1001 X
b1 Z
1*
#40200
0*
#40300
b1010 X
b10 Z
1*
#40400
0*
#40500
bz0 !
bz0 5
04
03
b0 X
02
b0 Z
1*
#40600
0*
#40700
b1 X
b1 Z
1*
#40800
0*
#40900
b10 X
b10 Z
1*
#41000
0*
#41100
b10011000 '
b10011000 ;
b10011000 ?
b1001 <
b101001 1
b101001 ^
b10011000 #
b10011000 7
b10011000 O
b11101 ]
b1001 L
b11101 /
b11101 [
b101001 0
b101001 T
b101001 V
bz1 !
bz1 5
14
b11 X
12
b0 Z
1*
#41200
0*
#41300
b100 X
b1 Z
1*
#41400
0*
#41500
b101 X
b10 Z
1*
#41600
0*
#41700
bz0 !
bz0 5
04
b110 X
02
b0 Z
1*
#41800
0*
#41900
b111 X
b1 Z
1*
#42000
0*
#42100
b1000 X
b10 Z
1*
#42200
0*
#42300
b11000000 '
b11000000 ;
b11000000 ?
b10110000 &
b10110000 :
b10110000 C
b0 <
b11 @
b10110000 "
b10110000 6
b10110000 S
b110000 1
b110000 ^
b11 .
b11 P
b11000000 #
b11000000 7
b11000000 O
b11110 ]
b0 L
b11110 /
b11110 [
b110000 0
b110000 T
b110000 V
bz1 !
bz1 5
14
b1001 X
12
b0 Z
1*
#42400
0*
#42500
b1010 X
b1 Z
1*
#42600
0*
#42700
13
b0 X
b10 Z
1*
#42800
0*
#42900
bz0 !
bz0 5
04
b1 X
02
b0 Z
1*
#43000
0*
#43100
b10 X
b1 Z
1*
#43200
0*
#43300
b11 X
b10 Z
1*
#43400
0*
