Digital Logic Class/Lab2/week2.v
module week2 (input a, input b, input c, input d, output reg f);

always @ (a, b, c, d)
    case ({a,c,d,b})
        0:  f = 1;
        3:  f = 1;
        5:  f = 1;
        6:  f = 1;
        9:  f = 1;
        10: f = 1;
        12: f = 1;
        15: f = 1;
        default:  f = 0;
    endcase 

endmodule

Digital Logic Class/Lab2/tb.v
`timescale 1 ns / 100 ps

module tb();

reg a, b, c, d;
wire f;

week2 DUT (.a(a), .b(b), .c(c), .d(d), .f(f));


initial
  begin
    $dumpfile("week2.vcd");
	$dumpvars;
       a = 0; b = 0; c = 0; d = 0;
   #10 a = 0; b = 0; c = 0; d = 1;
   #10 a = 0; b = 0; c = 1; d = 0;
   #10 a = 0; b = 0; c = 1; d = 1;
   #10 a = 0; b = 1; c = 0; d = 0;
   #10 a = 0; b = 1; c = 0; d = 1;
   #10 a = 0; b = 1; c = 1; d = 0;
   #10 a = 0; b = 1; c = 1; d = 1;
   #10 a = 1; b = 0; c = 0; d = 0;
   #10 a = 1; b = 0; c = 0; d = 1;
   #10 a = 1; b = 0; c = 1; d = 0;
   #10 a = 1; b = 0; c = 1; d = 1;
   #10 a = 1; b = 1; c = 0; d = 0;
   #10 a = 1; b = 1; c = 0; d = 1;
   #10 a = 1; b = 1; c = 1; d = 0;
   #10 a = 1; b = 1; c = 1; d = 1;
   #10 $finish;
  end
  
initial
  begin
    $monitor($time, "a = %b, b = %b, c = %b, d = %b, f = %b",
	         a, b, c, d, f);
  end

endmodule

Digital Logic Class/Lab2/week2.vcd
$date
	Wed Sep 09 04:46:47 2020
$end
$version
	Icarus Verilog
$end
$timescale
	100ps
$end
$scope module tb $end
$var wire 1 ! f $end
$var reg 1 " a $end
$var reg 1 # b $end
$var reg 1 $ c $end
$var reg 1 % d $end
$scope module DUT $end
$var wire 1 " a $end
$var wire 1 # b $end
$var wire 1 $ c $end
$var wire 1 % d $end
$var reg 1 ! f $end
$upscope $end
$upscope $end
$enddefinitions $end
#0
$dumpvars
0%
0$
0#
0"
1!
$end
#100
0!
1%
#200
0%
1$
#300
1!
1%
#400
0!
0%
0$
1#
#500
1!
1%
#600
0%
1$
#700
0!
1%
#800
0%
0$
0#
1"
#900
1!
1%
#1000
0%
1$
#1100
0!
1%
#1200
1!
0%
0$
1#
#1300
0!
1%
#1400
0%
1$
#1500
1!
1%
